molecule_virtup/__init__.py
molecule_virtup/driver.py
molecule_virtup/cookiecutter/cookiecutter.json
molecule_virtup/cookiecutter/{{cookiecutter.molecule_directory}}/{{cookiecutter.scenario_name}}/INSTALL.rst
molecule_virtup/modules/__init__.py
molecule_virtup/modules/virt_up.py
molecule_virtup/playbooks/create.yml
molecule_virtup/playbooks/destroy.yml
molecule_virtup/playbooks/prepare.yml
molecule_virtup-1.5.0.dist-info/LICENSE
molecule_virtup-1.5.0.dist-info/METADATA
molecule_virtup-1.5.0.dist-info/WHEEL
molecule_virtup-1.5.0.dist-info/entry_points.txt
molecule_virtup-1.5.0.dist-info/top_level.txt
molecule_virtup-1.5.0.dist-info/RECORD
