Metadata-Version: 2.1
Name: molecule-virtup
Version: 1.5.0
Summary: virt-up Molecule Plugin :: run molecule tests using virt-up
Home-page: https://github.com/meffie/molecule-virtup
Author: Michael Meffie
Author-email: mmeffie@sinenomine.net
License: UNKNOWN
Platform: UNKNOWN
Classifier: Programming Language :: Python :: 3
Classifier: License :: OSI Approved :: MIT License
Classifier: Operating System :: OS Independent
Requires-Python: >=3.6
Requires-Dist: molecule (>=3.2.0)
Requires-Dist: pyyaml (<6,>=5.1)
